sqlalchemy_async_mixin-0.1.0.dist-info/METADATA
sqlalchemy_async_mixin-0.1.0.dist-info/WHEEL
sqlalchemy_async_mixin/__init__.py
sqlalchemy_async_mixin-0.1.0.dist-info/RECORD
