Metadata-Version: 2.1
Name: sqlalchemy_async_mixin
Version: 0.1.0
Summary: Default template for PDM package
Author-Email: PdcShoun <pdc.pachara@gmail.com>
License: MIT
Requires-Python: >=3.8
Requires-Dist: sqlalchemy[asyncio]>=2.0.29
